itssutils/__init__.py
itssutils/itssdata.py
itssutils/loader/__init__.py
itssutils/loader/consolidator.py
itssutils/loader/date_processor.py
itssutils/loader/decoder.py
itssutils/loader/load_raw.py
itssutils/metrics/__init__.py
itssutils/metrics/metrics.py
itssutils/metrics/names.py
itssutils/metrics/zscores.py
itssutils/population/__init__.py
itssutils/population/get_census_data.py
itssutils/utils/__init__.py
itssutils/utils/secrets.py
itssutils/viz/__init__.py
itssutils/viz/barplot.py
itssutils/viz/plot_config.py
itssutils/viz/ratioplot.py
itssutils/viz/scatterplot.py
itssutils/viz/timeseries.py
itssutils/viz/zhist.py
itssutils-0.0.1.dist-info/LICENSE
itssutils-0.0.1.dist-info/METADATA
itssutils-0.0.1.dist-info/WHEEL
itssutils-0.0.1.dist-info/top_level.txt
itssutils-0.0.1.dist-info/RECORD
