Metadata-Version: 2.1
Name: itssutils
Version: 0.0.1
Summary: Utilities for analyzing Illinois Traffic Stop Study data.
Home-page: http://github.com/JustDSOrg/itssutils
Author: Chris Kucharczyk
Author-email: chris.kucharczyk@gmail.com
License: MIT
Platform: UNKNOWN
Classifier: Programming Language :: Python :: 3
Classifier: License :: OSI Approved :: MIT License
Classifier: Operating System :: OS Independent
Requires-Dist: pandas
Requires-Dist: numpy
Requires-Dist: scipy
Requires-Dist: matplotlib
Requires-Dist: tqdm
Requires-Dist: statsmodels
